{"doc":" @author kyc\n @date 2024/2/23 14:26\n","fields":[],"enumConstants":[],"methods":[{"name":"queryArmoryList","paramTypes":["com.ruoyi.business.domain.bo.BizProductBo","com.ruoyi.common.core.domain.PageQuery"],"doc":" 兵棋库\n\n @param bo\n @param pageQuery\n @return\n"},{"name":"queryArmoryDetail","paramTypes":["com.ruoyi.business.domain.bo.BizProductBo"],"doc":" 兵棋详情\n\n @param queryArmoryDetailDto\n @return\n"},{"name":"queryArmoryRuleDetail","paramTypes":["com.ruoyi.business.domain.bo.BizProductBo"],"doc":" 规则了解\n\n @param queryArmoryDetailDto\n @return\n"},{"name":"queryVerdictScenarioVos","paramTypes":["com.ruoyi.business.domain.bo.BizProductBo"],"doc":" 智能裁决-想定选择列表\n\n @param queryArmoryDetailDto\n @return\n"},{"name":"queryVerdictScenarioDetail","paramTypes":["com.ruoyi.business.domain.bo.BizScenarioBo"],"doc":" 智能裁决-想定选择详情\n\n @param queryVerdictScenarioDetailDto\n @return\n"},{"name":"saveVerdictScenario","paramTypes":["com.ruoyi.business.domain.bo.BizVerdictRecordBo"],"doc":" 智能裁决-选择想定\n\n @param saveVerdictScenarioDto\n @return\n"},{"name":"queryVerdictChessPiecesVos","paramTypes":["com.ruoyi.business.domain.vo.BizProductVo"],"doc":" 智能裁决-棋子选择列表\n\n @param queryArmoryDetailDto\n @return\n"},{"name":"queryVerdictChessPiecesDetail","paramTypes":["com.ruoyi.business.domain.bo.BizChessPiecesBo"],"doc":" 智能裁决-棋子选择详情\n\n @param queryVerdictChessPiecesDetailDto\n @return\n"},{"name":"saveVerdictChessPieces","paramTypes":["com.ruoyi.business.domain.bo.BizChessPiecesBo"],"doc":" 智能裁决-选择棋子\n\n @param saveVerdictChessPiecesDto\n @return\n"},{"name":"generateInviteCode","paramTypes":["java.lang.Long"],"doc":" 生成邀请码\n\n @return\n"},{"name":"joinRoom","paramTypes":["java.lang.String","java.lang.String"],"doc":" 加入房间\n\n @return\n"},{"name":"inviteFriend","paramTypes":["com.ruoyi.business.domain.bo.BizVerdictRecordBo"],"doc":" 邀请人输入邀请码-用以邀请他人参赛\n\n @param inviteFriendDto\n @return\n"},{"name":"responseInvite","paramTypes":["com.ruoyi.business.domain.bo.BizVerdictRecordBo"],"doc":" 响应参赛邀请\n\n @param responseInviteDto\n @return\n"},{"name":"queryCampList","paramTypes":["com.ruoyi.business.domain.bo.BizChessPiecesCampBo"],"doc":" 角色选择-查询棋子阵营\n\n @param queryCampDto\n @return\n"},{"name":"chooseCamp","paramTypes":["com.ruoyi.business.domain.bo.BizChessPiecesCampBo"],"doc":" 选择阵营\n\n @param chooseCampDto\n @return\n"},{"name":"goVerdictRecordDetail","paramTypes":["com.ruoyi.business.domain.bo.BizVerdictRecordDetailBo"],"doc":" 进入裁决详情\n\n @param dto\n @return\n"},{"name":"targetChessPiecesNumberList","paramTypes":["com.ruoyi.business.domain.bo.BizVerdictRecordBo"],"doc":" 目标棋子编号列表\n\n @param dto\n @return\n"},{"name":"targetChessPiecesDetail","paramTypes":["com.ruoyi.business.domain.bo.BizChessPiecesBo"],"doc":" 目标棋子详情\n\n @param dto\n @return\n"},{"name":"verdict","paramTypes":["com.ruoyi.business.domain.bo.BizVerdictRecordDetailBo"],"doc":" 裁决\n\n @param dto\n @return\n"},{"name":"startGame","paramTypes":["com.ruoyi.business.domain.bo.BizVerdictRecordBo"],"doc":" 开始游戏\n\n @param startGameDto\n @return\n"},{"name":"queryGameStatus","paramTypes":["com.ruoyi.business.domain.bo.BizVerdictRecordBo"],"doc":" 查询游戏状态\n\n @param dto\n @return\n"},{"name":"queryRoomUser","paramTypes":["com.ruoyi.business.domain.bo.BizVerdictRecordBo"],"doc":" 查询房间内用户信息\n\n @param dto\n @return\n"},{"name":"queryVerdictId","paramTypes":["com.ruoyi.business.domain.bo.BizVerdictRecordBo"],"doc":" 查询裁决ID\n\n @param dto\n @return\n"},{"name":"deployChessPieces","paramTypes":["com.ruoyi.business.domain.bo.BizVerdictRecordHistoryBo"],"doc":" 部署棋子\n\n @param dto\n @return\n"},{"name":"deployScenarioChessPieces","paramTypes":["com.ruoyi.business.domain.bo.BizScenarioRecordHistoryBo"],"doc":" 想定部署棋子\n\n @param dto\n @return\n"},{"name":"endDeploy","paramTypes":["com.ruoyi.business.domain.bo.BizVerdictRecordHistoryBo"],"doc":" 结束部署\n\n @param dto\n @return\n"},{"name":"queryChessRound","paramTypes":["com.ruoyi.business.domain.bo.BizVerdictRecordBo"],"doc":" 查询回合数\n\n @param dto\n @return\n"},{"name":"isOwnRound","paramTypes":["com.ruoyi.business.domain.bo.BizVerdictRecordBo"],"doc":" 是否自己回合\n\n @param dto\n @return\n"},{"name":"chessPiecesAction","paramTypes":["com.ruoyi.business.domain.bo.BizVerdictRecordDetailBo"],"doc":" 棋子行动\n\n @param dto\n @return\n"},{"name":"queryEachAction","paramTypes":["com.ruoyi.business.domain.bo.BizVerdictRecordBo"],"doc":" 查询每步行动\n\n @param dto\n @return\n"},{"name":"queryActionEffect","paramTypes":["com.ruoyi.business.domain.bo.BizVerdictRecordBo"],"doc":" 查询攻击效果\n\n @param dto\n @return\n"},{"name":"queryVerdictResult","paramTypes":["com.ruoyi.business.domain.bo.BizVerdictRecordBo"],"doc":" 查询比赛结果\n\n @param dto\n @return\n"},{"name":"endRound","paramTypes":["com.ruoyi.business.domain.bo.BizVerdictRecordBo"],"doc":" 结束回合\n\n @param dto\n @return\n"},{"name":"queryPrompt","paramTypes":["com.ruoyi.business.domain.bo.BizVerdictRecordBo"],"doc":" 查询提示信息\n\n @param dto\n @return\n"},{"name":"endGame","paramTypes":["com.ruoyi.business.domain.bo.BizVerdictRecordBo"],"doc":" 结束游戏\n\n @param dto\n @return\n"},{"name":"queryChessPiecesInfo","paramTypes":["com.ruoyi.business.domain.bo.BizVerdictRecordBo"],"doc":" 查询棋子位置及状态等信息-根据单个棋子查询\n\n @param dto\n @return\n"},{"name":"queryAllChessPiecesInfo","paramTypes":["com.ruoyi.business.domain.dto.QueryAllChessPiecesInfoDto"],"doc":" 查询裁决中所有棋子位置及状态等信息\n\n @param dto\n @return\n"},{"name":"queryAllChessPiecesInfoC","paramTypes":["com.ruoyi.business.domain.dto.QueryAllScenarioChessPiecesInfoDto"],"doc":" 插入对应的创建想定所有棋子位置及状态等信息\n\n @param dto\n @return\n"},{"name":"creatVerdictRoom","paramTypes":["com.ruoyi.business.domain.dto.CreatVerdictRoomInfoDto"],"doc":" 插入对应的创建想定所有棋子位置及状态等信息\n\n @param dto\n @return\n"},{"name":"queryUsChessPiecesInfo","paramTypes":["com.ruoyi.business.domain.dto.QueryAllChessPiecesInfoDto"],"doc":" 查询裁决中我方棋子信息\n\n @param dto\n @return\n"},{"name":"queryMapInfo","paramTypes":["com.ruoyi.business.domain.bo.BizVerdictRecordBo"],"doc":" 查询地图信息\n\n @param dto\n @return\n"},{"name":"queryUnfinishedList","paramTypes":["com.ruoyi.business.domain.bo.BizVerdictRecordBo","com.ruoyi.common.core.domain.PageQuery"],"doc":" 复盘列表\n\n @param search\n @return\n"},{"name":"queryVerdictRecordList","paramTypes":["com.ruoyi.business.domain.bo.BizVerdictRecordBo","com.ruoyi.common.core.domain.PageQuery"],"doc":" 复盘列表\n\n @param search\n @return\n"},{"name":"chessPiecesActionHistory","paramTypes":["com.ruoyi.business.domain.bo.BizVerdictRecordBo"],"doc":" 棋子行动历史复盘\n\n @param dto\n @return\n"},{"name":"globalVision","paramTypes":["com.ruoyi.business.domain.bo.BizVerdictRecordBo"],"doc":" 全局视野\n\n @param dto\n @return\n"},{"name":"queryScoreList","paramTypes":["com.ruoyi.business.domain.bo.BizVerdictRecordScoreBo"],"doc":" 获取查分结果\n\n @param bo\n @return\n"},{"name":"getRealTimeScore","paramTypes":["com.ruoyi.business.domain.bo.BizVerdictRecordScoreBo"],"doc":" 查询实时分数\n\n @param bo\n @return\n"},{"name":"judge","paramTypes":["com.ruoyi.business.domain.bo.BizVerdictRecordRoundBo"],"doc":" 查询回合提交状态\n\n @param bo\n @return\n"},{"name":"getRoundStatus","paramTypes":["com.ruoyi.business.domain.bo.BizVerdictRecordRoundBo"],"doc":" 查询回合提交状态\n\n @param bo\n @return\n"},{"name":"saveTextInstruction","paramTypes":["com.ruoyi.business.domain.bo.BizVerdictRecordRoundBo"],"doc":" 保存文本指令\n\n @param bo 包含roundId和textIns的对象\n @return 成功返回success\n"}],"constructors":[]}